{
  "id": "$X1HEYUXBQ",
  "scale": {
    "id": "$ALVVCT-93",
    "title": "آزمون بررسی ارزش‌های آلپورت فرم الف"
  },
  "chain": null,
  "version": "1",
  "edition": "",
  "edition_version": null,
  "client": {
    "id": "GH96CXXXX",
    "name": "مراجع",
    "user_id": "IR96XXXX"
  },
  "room": {
    "id": "RS9XXXX",
    "manager": {
      "id": "GH96XXXX",
      "name": "درمانگر",
      "user_id": "IR9XXXX"
    },
    "center": {
      "id": "RS96XXXXX",
      "acceptation": null,
      "status": "active",
      "type": "counseling_center",
      "detail": {
        "title": "مرکز"
      }
    },
    "acceptation": null,
    "status": "active",
    "type": "room"
  },
  "case": null,
  "code": null,
  "created_at": 1735575313,
  "started_at": 1735577578,
  "scored_at": 1735628807,
  "closed_at": 1735578336,
  "total_amount": 0,
  "prepayment": true,
  "purchased": false,
  "amount": 0,
  "billing": null,
  "description": null,
  "psychologist_description": null,
  "items": [
    {
      "type": "two_side",
      "category": "بخش اول",
      "text": "به نظر شما تحقیقات علمی بیشتر متوجه چه هدفی باید باشد؟",
      "sides": ["کشف حقیقت", "استفاده‌های عملی"],
      "answer": { "type": "range", "min": 1, "max": 4 },
      "user_answered": "4"
    },
    {
      "type": "two_side",
      "category": "بخش اول",
      "text": "کتب آسمانی به طور کلی از چه لحاظ برای شما جالب توجه هستند ؟",
      "sides": ["از نظر قدرت بیان و داستان‌های زیبا", "از نظر جنبه‌های روحانی"],
      "answer": { "type": "range", "min": 1, "max": 4 },
      "user_answered": "3"
    },
    {
      "type": "two_side",
      "category": "بخش اول",
      "text": "کدام‌یک از افراد زیر سهم بیشتری در پیشرفت تمدن بشری داشته‌اند؟",
      "sides": ["ابن‌سینا", "کاوه آهنگر"],
      "answer": { "type": "range", "min": 1, "max": 4 },
      "user_answered": "1"
    },
    {
      "type": "two_side",
      "category": "بخش اول",
      "text": "به فرض اینکه استعداد و شایستگی یکسان برای دو شغل زیر داشته باشید ، کدامیک را انتخاب می‌کنید؟",
      "sides": ["تجارت", "وزارت"],
      "answer": { "type": "range", "min": 1, "max": 4 },
      "user_answered": "1"
    },
    {
      "type": "two_side",
      "category": "بخش اول",
      "text": "آیا به نظر شما صحیح است که هنرمندان بزرگ در هنر خود فقط احساسات خود را در نظر بگیرند و به تمایلات دیگران توجهی نداشته باشند؟",
      "sides": ["بلی", "خیر"],
      "answer": { "type": "range", "min": 1, "max": 4 },
      "user_answered": "1"
    },
    {
      "type": "two_side",
      "category": "بخش اول",
      "text": "به نظر شما تحصیل درکدامیک از رشته‌های زیر برای بشریت اهمیت بیشتری دارد ؟",
      "sides": ["ریاضیات ", "الهیات"],
      "answer": { "type": "range", "min": 1, "max": 4 },
      "user_answered": "3"
    },
    {
      "type": "two_side",
      "category": "بخش اول",
      "text": "به نظر شما رهبران اجتماع به کدام‌یک از کارهای زیر باید بیشتر توجه کنند؟",
      "sides": [
        "کوشش برای انجام برنامه‌های سودمند و عملی",
        "تشویق پیروان خود به رعایت حقوق دیگران"
      ],
      "answer": { "type": "range", "min": 1, "max": 4 },
      "user_answered": "3"
    },
    {
      "type": "two_side",
      "category": "بخش اول",
      "text": "در جشن‌ها ومراسم با شکوه بیشتر تحت تأثیر چه چیزی واقع می‌شوید؟",
      "sides": [
        "شکوه و زیبایی خود جشن‌ها",
        "نفوذ و قدرت برگزار کنندگان جشن‌ها"
      ],
      "answer": { "type": "range", "min": 1, "max": 4 },
      "user_answered": "3"
    },
    {
      "type": "two_side",
      "category": "بخش اول",
      "text": "کدامیک از این دو خصوصیت را مهمتر می‌دانید؟",
      "sides": [
        "پایبندی به ارزش‌های روحانی و تعالیم مذهبی",
        "نوع دوستی و کمک به دیگران"
      ],
      "answer": { "type": "range", "min": 1, "max": 4 },
      "user_answered": "4"
    },
    {
      "type": "two_side",
      "category": "بخش اول",
      "text": "اگر هم در ادبیات و هم در فیزیک تخصص کافی داشتید تدریس کدامیک از دو رشته را در دانشگاه ترجیح می‌دادید؟",
      "sides": ["ادبیات", "فیزیک"],
      "answer": { "type": "range", "min": 1, "max": 4 },
      "user_answered": "4"
    },
    {
      "type": "two_side",
      "category": "بخش اول",
      "text": "از دو کتاب روبرو خواندن کدامیک را ترجیح خواهید داد؟",
      "sides": ["نقش مذهب در دنیای امروز", "عوامل رشد اقتصادی"],
      "answer": { "type": "range", "min": 1, "max": 4 },
      "user_answered": "4"
    },
    {
      "type": "two_side",
      "category": "بخش اول",
      "text": "از دو مقاله روبرو که در روزنامه چاپ شده است کدامیک را دقیق‌تر می‌خوانید؟",
      "sides": ["سازمان ملل در ده سال گذشته", "یک نظریه جدید علمی اعلام شده"],
      "answer": { "type": "range", "min": 1, "max": 4 },
      "user_answered": "4"
    },
    {
      "type": "two_side",
      "category": "بخش اول",
      "text": "در بازدید از اماکن مقدس بیشتر تحت تأثیر چه چیز واقع می‌شوید؟",
      "sides": ["احساسات مذهبی", "سبک معماری و تزئینات"],
      "answer": { "type": "range", "min": 1, "max": 4 },
      "user_answered": "1"
    },
    {
      "type": "two_side",
      "category": "بخش اول",
      "text": "در صورت داشتن وقت و فراغت کافی کدامیک از دو فعالیت زیر را ترجیح می‌دهید؟",
      "sides": ["کار آموزی در یک حرفه جالب", "فعالیت افتخاری در موسسه خیریه"],
      "answer": { "type": "range", "min": 1, "max": 4 },
      "user_answered": "2"
    },
    {
      "type": "two_side",
      "category": "بخش اول",
      "text": "در بازدید از یک نمایشگاه به دیدن کدام قسمت آن بیشتر علاقه‌مندید؟",
      "sides": ["محصولات صنعتی", "وسایل علمی و آزمایشگاهی"],
      "answer": { "type": "range", "min": 1, "max": 4 },
      "user_answered": "2"
    },
    {
      "type": "two_side",
      "category": "بخش اول",
      "text": "در کدامیک از دو بحث زیر بیشتر مایلید شرکت کنید؟",
      "sides": ["روابط ایران با کشورهای خارجی", "هنر معاصر ایران"],
      "answer": { "type": "range", "min": 1, "max": 4 },
      "user_answered": "4"
    },
    {
      "type": "two_side",
      "category": "بخش اول",
      "text": "هدف مذاهب در حال حاضر بیشتر چه باید باشد؟",
      "sides": [
        "توسعه تمایلات خیرخواهانه و نوع‌دوستانه",
        "تشویق به پرستش خدا و ارتباط معنوی با خدا"
      ],
      "answer": { "type": "range", "min": 1, "max": 4 },
      "user_answered": "4"
    },
    {
      "type": "two_side",
      "category": "بخش اول",
      "text": "اگر فقط دو مجلۀ زیر در اختیار شما بود، خواندن کدامیک را ترجیح می‌دادید؟",
      "sides": ["علوم جدید", "هنر معاصر"],
      "answer": { "type": "range", "min": 1, "max": 4 },
      "user_answered": "2"
    },
    {
      "type": "two_side",
      "category": "بخش اول",
      "text": "شرکت در کدام‌یک از سخنرانیهای زیر برای شما جالب‌تر است؟",
      "sides": [
        "مقایسه مزایای نسبی حکومت انگستان و آمریکا",
        "مقایسه توسعه و رشد ادیان بزرگ"
      ],
      "answer": { "type": "range", "min": 1, "max": 4 },
      "user_answered": "1"
    },
    {
      "type": "two_side",
      "category": "بخش اول",
      "text": "به نظر شما کدام‌یک از این دو وظیفه آموزش و پرورش مهم‌تر است؟",
      "sides": [
        "آماده ساختن افراد برای تلاش و موقعیت فردی",
        "آماده ساختن افراد برای شرکت در فعالیت‌های اجتماعی و کمک به هم‌نوعان"
      ],
      "answer": { "type": "range", "min": 1, "max": 4 },
      "user_answered": "3"
    },
    {
      "type": "two_side",
      "category": "بخش اول",
      "text": "به مطالعه زندگی کدام دسته از مشاهیر زیر بیشتر علاقه دارید؟",
      "sides": ["اسکندر - نادرشاه - ناپلئون", "ارسطو - افلاطون - ابن‌سینا"],
      "answer": { "type": "range", "min": 1, "max": 4 },
      "user_answered": "1"
    },
    {
      "type": "two_side",
      "category": "بخش اول",
      "text": "کدامیک از مشخصات زیر را نشانه یک تمدن اصیل می‌دانید؟",
      "sides": [
        "برخورداری از دستاوردهای علم و صنعت",
        "وجود صمیمیت و محبت بین افراد"
      ],
      "answer": { "type": "range", "min": 1, "max": 4 },
      "user_answered": "2"
    },
    {
      "type": "two_side",
      "category": "بخش اول",
      "text": "اگر در یک سازمان صنعتی کار کنید( به فرض حقوق مساوی ) کدامیک از مشاغل زیر را انتخاب خواهید کرد؟",
      "sides": ["مشاوره مسائل خصوصی کارمندان", "یک شغل اداری"],
      "answer": { "type": "range", "min": 1, "max": 4 },
      "user_answered": "2"
    },
    {
      "type": "two_side",
      "category": "بخش اول",
      "text": "مطالعه کدام‌یک از دو کتاب زیر را ترجیح می‌دهید؟",
      "sides": ["تاریخچه مذهب در ایران", "تاریخچه صنعت در ایران"],
      "answer": { "type": "range", "min": 1, "max": 4 },
      "user_answered": "1"
    },
    {
      "type": "two_side",
      "category": "بخش اول",
      "text": "توجه به کدام‌یک از دو هدف زیر بیشتر به حال جامعه مفید است ؟",
      "sides": ["حقوق فردی و رفاه اجتماعی", "بررسی قوانین رفتار انسان"],
      "answer": { "type": "range", "min": 1, "max": 4 },
      "user_answered": "3"
    },
    {
      "type": "two_side",
      "category": "بخش اول",
      "text": "اگر در مقامی باشیدکه بتوانید یکی از دو کار زیر را انجام دهید کدام یک را ترجیح می‌دهید؟",
      "sides": ["بالا بردن سطح زندگی مردم", "هدایت افکار عمومی"],
      "answer": { "type": "range", "min": 1, "max": 4 },
      "user_answered": "4"
    },
    {
      "type": "two_side",
      "category": "بخش اول",
      "text": "شرکت در کدام‌یک از سخنرانی‌های زیر را ترجیح می‌دهید؟",
      "sides": ["پیشرفت خدمات اجتماعی در کشور", "نقاشان معاصر"],
      "answer": { "type": "range", "min": 1, "max": 4 },
      "user_answered": "1"
    },
    {
      "type": "two_side",
      "category": "بخش اول",
      "text": "کدام‌یک از نظرات زیر را در مورد پیدایش جهان بیشتر ترجیح می‌دهید؟",
      "sides": [
        "جهان مطابق قوانین طبیعی تحول یافته و هیچ نیروی ماورای طبیعی در پیدایش آن دخالت نداشته ",
        "جهان را خداوند آفریده است."
      ],
      "answer": { "type": "range", "min": 1, "max": 4 },
      "user_answered": "1"
    },
    {
      "type": "two_side",
      "category": "بخش اول",
      "text": "به مطالعه کدام‌یک از دو بخش زیر در روزنامه‌ها علاقه دارید؟",
      "sides": [
        "مطالعه مربوط به معاملات ملکی و نرخ اجناس",
        "مطالب مربوط به نمایشگاه‌ها و موزه‌های هنری"
      ],
      "answer": { "type": "range", "min": 1, "max": 4 },
      "user_answered": "4"
    },
    {
      "type": "two_side",
      "category": "بخش اول",
      "text": "چه نوع تعلیماتی را برای تأمین آتیه فرزند خود مهم‌تر می‌دانید ؟",
      "sides": ["مذهبی", "ورزشی"],
      "answer": { "type": "range", "min": 1, "max": 4 },
      "user_answered": "2"
    },
    {
      "type": "text",
      "text": "به عقیده شما یک دولت خوب به کدام‌یک از هدف‌های روبه‌رو باید بیشتر اهمیت دهد؟",
      "category": "بخش دوم",
      "answer": {
        "type": "sortable",
        "options": [
          "کمک به طبقات کم درآمد",
          "توسعه تجارت و صنعت",
          "پیروی از اصول عالی اخلاقی در سیاست‌های خود",
          "کسب احترام و حیثیت در بین ملت‌ها"
        ]
      },
      "user_answered": "2,1,4,3"
    },
    {
      "type": "text",
      "text": "به عقیده شما کسی که تمام هفته را کار می‌کند ، چگونه می تواند جمعه خود را به بهترین وجهی بگذراند؟",
      "category": "بخش دوم",
      "answer": {
        "type": "sortable",
        "options": [
          "مطالعه کتاب‌های ارزنده برای بالا بردن سطح دانش عمومی خود",
          "فعالیت‌ در ورزش‌های مورد علاقه",
          "بازدید از یک نمایشگاه یا موزه هنری",
          "کسب احترام و حیثیت در بین ملت‌ها"
        ]
      },
      "user_answered": "2,3,4,1"
    },
    {
      "type": "text",
      "text": "اگر در مقامی بودید که می‌توانستید روش آموزشی مدارس را تغییر دهید کدام‌یک از هدف‌های روبه‌رو را بیشتر دنبال می‌کردید؟",
      "category": "بخش دوم",
      "answer": {
        "type": "sortable",
        "options": [
          "کمک به پیشرفت آموزش موسیقی",
          "ترویج تحصیلات مربوط به مسائل اجتماعی",
          "توسعه تسهیلات آزمایشگاهی در مدارس",
          "تاکید بر فایده عملی درس‌ها در زندگی"
        ]
      },
      "user_answered": "2,4,3,1"
    },
    {
      "type": "text",
      "text": "از میان هم‌جنسان خود دوستی با چه آدمی را ترجیح می‌دهید؟",
      "category": "بخش دوم",
      "answer": {
        "type": "sortable",
        "options": [
          "لایق و کارا و عملی",
          "علاقه‌مند به بررسی فلسفه زندگی خود",
          "دارای شایستگی رهبری و مدیریت",
          "دارای عواطف لطیف و احساسات هنری"
        ]
      },
      "user_answered": "1,4,3,2"
    },
    {
      "type": "text",
      "text": "اگر در شهر کوچکی زندگی می‌کردید و درامدتان بیش از مایحتاجتان بود ترجیح می‌دادید اضافه درآمد خود را به چه نحوی مصرف کنید؟",
      "category": "بخش دوم",
      "answer": {
        "type": "sortable",
        "options": [
          "کمک به توسعه صنعت و تجارت",
          "کمک به توسعه تحقیقات علمی",
          "کمک به پیشرفت‌ فعالیت‌های مذهبی",
          "کمک به خانواده‌های بی‌بضاعت"
        ]
      },
      "user_answered": "1,2,4,3"
    },
    {
      "type": "text",
      "text": "از چه نوع فیلم‌هایی بیشتر لذت می‌برید؟",
      "category": "بخش دوم",
      "answer": {
        "type": "sortable",
        "options": [
          "فیلم‌های مربوط به زندگی مشاهیر",
          "فیلم‌هایی که صرف‌نظر از موضوع به طور کلی صدا و رنگ و شکل در آن‌ها زیبا به کار رفته است.",
          "فیلم‌هایی که موضوع اصلی آن‌ها رنج و محبت است",
          "فیلم‌هایی که در آ‌نها یک فکر یا یک نظریه مطرح می‌شود. "
        ]
      },
      "user_answered": "4,2,1,3"
    },
    {
      "type": "text",
      "text": "اگر توانایی لازم را برای انجام مشاغل روبرو داشتید ( به فرض حقوق مساوی )کدام‌یک را انتخاب می‌کردید؟",
      "category": "بخش دوم",
      "answer": {
        "type": "sortable",
        "options": ["ریاضی‌دان", "بازرگان ", "عالم روحانی", "سیاست‌مدار"]
      },
      "user_answered": "3,1,2,4"
    },
    {
      "type": "text",
      "text": "اگر پول و فراغت کافی در اختیار داشتید، کدامیک از فعالیت‌های روبرو را بیشتر ترجیح می‌دادید؟",
      "category": "بخش دوم",
      "answer": {
        "type": "sortable",
        "options": [
          "جمع‌آوری مجسمه یا نقاشی",
          "تاسیس مرکزی برای نگهداری و پرورش اطفال کودن",
          "فعالیت‌ برای به دست آوردن شغل وزارت یا نمایندگی مجلس",
          "تاسیس یک موسسه تجارتی یا مالی خصوصی"
        ]
      },
      "user_answered": "1,3,2,4"
    },
    {
      "type": "text",
      "text": "در مجلس عصرانه‌ای که عده‌ای از دوستان صمیمی (همجنس) دور هم جمع شده‌اید ، بیشتر مایلید دربارۀ چه مطالبی بحث کنید؟",
      "category": "بخش دوم",
      "answer": {
        "type": "sortable",
        "options": [
          "معنی و مفهوم زندگی",
          "پیشرفت‌های جدید علوم",
          "ادبیات",
          "رفاه اجتماعی"
        ]
      },
      "user_answered": "1,2,4,3"
    },
    {
      "type": "text",
      "text": "در تعطیلات تابستان آینده در صورت توانایی‌های لازم، اشتغال به کدام‌یک از فعالیت‌های روبرو را بیشتر ترجیح خواهید داد؟",
      "category": "بخش دوم",
      "answer": {
        "type": "sortable",
        "options": [
          "کار موقت در یک موسسه تحقیقات علمی",
          "استراحت در یک محل بی سر و صدا و لذت بردن از مناظر زیبای طبیعت",
          "مطالعه درباره زندگی رهبران",
          "شرکت در یک دوره کارآموزی حرفه‌ای "
        ]
      },
      "user_answered": "3,2,1,4"
    },
    {
      "type": "text",
      "text": "سفرهای اکتشافی اشخاص برجسته‌ای مانند کریستف کلمب و ماژلان برای کشف سرزمین‌های ناشناخته از چه لحاظ به نظر شما بیشتر مهم هستند؟",
      "category": "بخش دوم",
      "answer": {
        "type": "sortable",
        "options": [
          "غلبه بشر را بر نیروی طبیعت نشان می‌دهد",
          "معلومات ما را در زمینه جغرافیا ، هواشناسی و اقیانوس‌شناسی افزایش می‌دهد.",
          "موجب دوستی بیشتری بین افراد و ملت‌ها می‌شود.",
          "هر یک از این اکتشافات به سهم خود ما را در درک عظمت خداوند یاری می‌دهد."
        ]
      },
      "user_answered": "2,3,4,1"
    },
    {
      "type": "text",
      "text": "به نظر شما چه ملاکی باید اساس رفتارهای انسان قرار گیرد؟",
      "category": "بخش دوم",
      "answer": {
        "type": "sortable",
        "options": [
          "معتقدات مذهبی",
          "معیارهای زیبایی",
          "معیارهای گروه شغلی و همکاران",
          "معیارهای نوع دوستی"
        ]
      },
      "user_answered": "4,3,2,1"
    },
    {
      "type": "text",
      "text": "به کدام‌یک از مشاهیر زیر بیشتر علاقه‌مندید؟ و اگر استعداد کافی برای مشاغل زیرداشته باشید کدام‌یک را بیشتر ترجیح خواهید داد؟",
      "category": "بخش دوم",
      "answer": {
        "type": "sortable",
        "options": ["معلم", "فرماندار", "بازرگان", "محقق"]
      },
      "user_answered": "3,4,2,1"
    },
    {
      "type": "text",
      "text": "برای آقایان: چه نوع زنی را بیشتر مایلید به عنوان همسر خود انتخاب کنید",
      "description": "اگر آقا هستید به این سوال پاسخ دهید در غیر این‌صورت این سوال را بی‌پاسخ رهاکنید و به سراغ سوال بعدی بروید",
      "category": "بخش دوم",
      "answer": {
        "type": "sortable",
        "nullable": { "text": "زن هستم" },
        "options": [
          "سرزبان‌دار و اجتماعی",
          "علاقمند به کمک به دیگران",
          "پایبند اصول مذهبی ",
          "سرشار از استعداد هنری"
        ]
      },
      "user_answered": "4,2,3,1"
    },
    {
      "type": "text",
      "text": "برای خانم‌ها: چه نوع مردی را مایلید به عنوان شوهر خود انتخاب کنید؟",
      "description": "اگر خانم هستید به این سوال پاسخ دهید در غیر این‌صورت این سوال را بی‌پاسخ رهاکنید و سوال قبلی را پاسخ دهید",
      "answer": {
        "category": "بخش دوم",
        "nullable": { "text": "مرد هستم" },
        "type": "sortable",
        "options": [
          "در حرفه و کار خود موفق بوده و مورد تحسین دیگران باشد.",
          "علاقه‌مند به کمک کردن به دیگران باشد.",
          "در زندگی خود به طور کلی پایبند اصول مذهبی باشد.",
          " استعداد هنری داشته باشد."
        ]
      },
      "user_answered": "2,4,3,1"
    },
    {
      "type": "text",
      "text": "یک نسخۀ نفیس خطی قدیم قرآن از نظر شما یادآور چیست؟",
      "category": "بخش دوم",
      "answer": {
        "type": "sortable",
        "options": [
          "نشانه رابطه معنوی انسان با خدا است.",
          "یک اثر گران‌بها و نادر است.",
          "نشانه قدرت و نفوذ اسلام در جهان است.",
          "نشانه هماهنگی و زیبایی در هنر قدیم است"
        ]
      },
      "user_answered": "4,2,3,1"
    }
  ],
  "prerequisites": [
    {
      "type": "text",
      "label": "gender",
      "text": "جنسیت",
      "answer": { "type": "select", "options": ["زن", "مرد"] },
      "alias": "gender",
      "force": true,
      "user_answered": "1"
    },
    {
      "type": "text",
      "label": "age",
      "text": "سن",
      "answer": { "type": "number" },
      "alias": "age",
      "force": true,
      "user_answered": "50"
    },
    {
      "type": "text",
      "label": "education",
      "text": "تحصیلات",
      "answer": {
        "type": "select",
        "options": [
          "ابتدایی اول",
          "ابتدایی دوم",
          "متوسطه اول",
          "متوسطه دوم",
          "دیپلم",
          "کارشناسی",
          "کارشناسی ارشد",
          "پزشکی عمومی",
          "متخصص",
          "دکتری تخصصی",
          "حوزوی مقدمات",
          "حوزوی سطح۱",
          "حوزوی سطح۲",
          "حوزوی سطح۳",
          "حوزوی سطح۴"
        ]
      },
      "alias": "education",
      "force": true,
      "user_answered": "8"
    },
    {
      "type": "text",
      "label": "marital_status",
      "text": "وضعیت تأهل",
      "answer": { "type": "select", "options": ["مجرد", "متأهل"] },
      "alias": "marital_status",
      "force": true,
      "user_answered": "1"
    }
  ],
  "entities": [
    {
      "offset": 0,
      "title": "بخش اول",
      "description": "این بخش شامل ۳۰ سؤال است که برای هر سؤال دو گزینه پاسخ انتخاب شده و این گزینه‌ها در دو طیف مختلف ارائه شده‌اند.\n\nاگر فکر می‌کنید دیدگاه شما کاملاً به یکی از دو طرف متمایل است، گزینه‌ای را انتخاب کنید که به آن نزدیک‌تر است. اگر تمایل شما کامل نیست اما همچنان به طرف دیگر برتری دارد، گزینه‌ای را انتخاب کنید که به طرف مطلوب نزدیک‌تر باشد."
    },
    {
      "offset": 30,
      "title": "بخش دوم",
      "description": "این بخش شامل ۱۵ سؤال است که برای هر سؤال چهار گزینه مختلف در نظر گرفته شده است.\n\nلطفاً این گزینه‌ها را بر اساس اهمیت برای خودتان مرتب کنید. به این صورت که گزینه‌ای که برایتان مهم‌تر است را در اولویت اول قرار دهید و بقیه گزینه‌ها را به ترتیب از دوم تا چهارم مشخص کنید.\n\nمثال: در اوقات فراغت ترجیح می‌دهید چه نوع کتاب‌هایی را بخوانید؟\n\n الف- داستانی.     ب-علمی و فنی.     ج- سیاسی.      د-مذهبی.\n\nاگر شما کتاب‌های داستانی را بیشتر از همه می‌پسندید در پاسخنامه به پاسخ الف نمره 4 بدهید . اگر بعد از کتاب‌های داستانی برای شما کتاب‌های مذهبی اهمیت دارد به پاسخ ب نمره 3 بدهید. اگر انتخاب سوم و چهارم شما به ترتیب کتابهای علمی و فنی و کتابهای سیاسی باشد زیر حروف ج و د و به ترتیب باید 2 و 1 بنویسید. حالا پاسخ خود را به سؤال فوق در نمونه پاسخ‌نامه که در زیر می‌بینید، بنویسید.\n\n\n\nترتیب پاسخ‌هایتان میزان اهمیت آن‌ها را برای شما نشان می‌دهد، بنابراین لطفاً سریع پاسخ دهید و زمان خود را روی یک سؤال خاص تلف نکنید.\n\nلطفاً به همه سؤالات پاسخ دهید."
    }
  ],
  "cornometer": 0,
  "score": {
    "theoretical_raw": 43,
    "theoretical_percentage": 0.614,
    "economic_raw": 44,
    "economic_percentage": 0.629,
    "aesthetic_raw": 41,
    "aesthetic_percentage": 0.586,
    "social_raw": 39,
    "social_percentage": 0.557,
    "political_raw": 37,
    "political_percentage": 0.529,
    "religious_raw": 36,
    "religious_percentage": 0.514
  },
  "score_current_version": "1.0.0",
  "score_last_version": "1.0.0"
}
