{
  "id": "$X1HXXXXX",
  "scale": {
    "id": "$JPIQ-93",
    "title": "پرسشنامه 16 عاملی شخصیت کتل"
  },
  "chain": null,
  "version": "2",
  "edition": "",
  "edition_version": null,
  "client": {
    "id": "GH966XXXX",
    "name": "مراجع"
  },
  "room": {
    "id": "RS96XXXX",
    "manager": {
      "id": "GH9XXXXX",
      "name": "درمانگر",
      "user_id": "IR9XXXX"
    },
    "center": {
      "id": "RS966XXXX",
      "acceptation": null,
      "status": "active",
      "type": "personal_clinic",
      "detail": {
        "title": "درمانگر"
      }
    },
    "acceptation": null,
    "status": "active",
    "type": "personal_clinic"
  },
  "case": null,
  "code": null,
  "created_at": 1694157079,
  "started_at": 1694157198,
  "scored_at": 1694242467,
  "closed_at": 1694160574,
  "total_amount": 100000,
  "prepayment": true,
  "purchased": true,
  "amount": 100000,
  "description": "پاسخگوی گرامی؛ \n\nلطفا رابطه خود و همسرتان را براساس جملات جدول زیر ارزیابی و درست بودن (درباره شما صدق می‌کند و با آن موافقید) یا نادرست بودن (درباره شما صدق نمی‌کند و با آن مخالفید) آن را درباره رابطه خودتان در جدول مقابل علامت بزنید.",
  "psychologist_description": null,
  "items": [
    {
      "type": "text",
      "text": "معمولاً وقتی اختلاف داریم پای خانواده‌ها به میان می‌آید.",
      "answer": {
        "type": "optional",
        "options": [
          "کاملاً درست",
          "تقریباً درست",
          "تا حدی درست",
          "تقریباً نادرست",
          "کاملاً نادرست"
        ]
      },
      "user_answered": "5"
    },
    {
      "type": "text",
      "text": "ارتباط با خانواده‌هایمان اختلافات ما را بیشتر می‌کند.",
      "answer": {
        "type": "optional",
        "options": [
          "کاملاً درست",
          "تقریباً درست",
          "تا حدی درست",
          "تقریباً نادرست",
          "کاملاً نادرست"
        ]
      },
      "user_answered": "5"
    },
    {
      "type": "text",
      "text": "وقتی که من و همسرم به نوعی با فرد دیگری در ارتباطیم، اثر دیگری بر من بیشتر از همسرم است.",
      "answer": {
        "type": "optional",
        "options": [
          "کاملاً درست",
          "تقریباً درست",
          "تا حدی درست",
          "تقریباً نادرست",
          "کاملاً نادرست"
        ]
      },
      "user_answered": "5"
    },
    {
      "type": "text",
      "text": "اگر خانواده و دیگری حذف شوند بین و همسرم مشکلات کاهش می‌یابد.",
      "answer": {
        "type": "optional",
        "options": [
          "کاملاً درست",
          "تقریباً درست",
          "تا حدی درست",
          "تقریباً نادرست",
          "کاملاً نادرست"
        ]
      },
      "user_answered": "2"
    },
    {
      "type": "text",
      "text": "وقتی میزان تماس تلفنی با خانواده/ دیگران زیاد می‌شود اختلافات ما افزایش می‌یابد.",
      "answer": {
        "type": "optional",
        "options": [
          "کاملاً درست",
          "تقریباً درست",
          "تا حدی درست",
          "تقریباً نادرست",
          "کاملاً نادرست"
        ]
      },
      "user_answered": "3"
    },
    {
      "type": "text",
      "text": "وقتی میزان تماس حضوری با خانواده/ دیگران زیاد می‌شود اختلافات ما زیاد می‌شود.",
      "answer": {
        "type": "optional",
        "options": [
          "کاملاً درست",
          "تقریباً درست",
          "تا حدی درست",
          "تقریباً نادرست",
          "کاملاً نادرست"
        ]
      },
      "user_answered": "4"
    },
    {
      "type": "text",
      "text": "تبادل اطلاعات غیر ضروری با دیگران زیاد است.",
      "answer": {
        "type": "optional",
        "options": [
          "کاملاً درست",
          "تقریباً درست",
          "تا حدی درست",
          "تقریباً نادرست",
          "کاملاً نادرست"
        ]
      },
      "user_answered": "5"
    },
    {
      "type": "text",
      "text": "نمی‌توانم در برابر کنجکاوی‌های دیگران نسبت به خانواده‌ام مقاومت کنم.",
      "answer": {
        "type": "optional",
        "options": [
          "کاملاً درست",
          "تقریباً درست",
          "تا حدی درست",
          "تقریباً نادرست",
          "کاملاً نادرست"
        ]
      },
      "user_answered": "4"
    },
    {
      "type": "text",
      "text": "وقتی نیازهای عاطفی‌ام از جانب همسر تأمین نمی‌شود برای جبران به دیگران (خانواده) مراجعه می‌کنم.",
      "answer": {
        "type": "optional",
        "options": [
          "کاملاً درست",
          "تقریباً درست",
          "تا حدی درست",
          "تقریباً نادرست",
          "کاملاً نادرست"
        ]
      },
      "user_answered": "2"
    },
    {
      "type": "text",
      "text": "وقتی خانواده‌ام نظری داشته باشند دیدگاه متفاوت همسرم برایم قابل پذیرش نیست.",
      "answer": {
        "type": "optional",
        "options": [
          "کاملاً درست",
          "تقریباً درست",
          "تا حدی درست",
          "تقریباً نادرست",
          "کاملاً نادرست"
        ]
      },
      "user_answered": "3"
    },
    {
      "type": "text",
      "text": "در تصمیم‌گیری‌ها درباره خانواده، نظر همسرم را بر نظر همه ترجیح می‌دهم.",
      "answer": {
        "type": "optional",
        "options": [
          "کاملاً درست",
          "تقریباً درست",
          "تا حدی درست",
          "تقریباً نادرست",
          "کاملاً نادرست"
        ]
      },
      "user_answered": "2"
    },
    {
      "type": "text",
      "text": "وقتی خانواده‌ام پیشنهادی می‌دهد بدون مشورت با همسرم عمل نمی‌کنم.",
      "answer": {
        "type": "optional",
        "options": [
          "کاملاً درست",
          "تقریباً درست",
          "تا حدی درست",
          "تقریباً نادرست",
          "کاملاً نادرست"
        ]
      },
      "user_answered": "1"
    },
    {
      "type": "text",
      "text": "هر چند برای دیگران (به ویژه والدین) احترام قائلم، نمی‌گذارم در مسائل داخلی خانواده مداخله کنند.",
      "answer": {
        "type": "optional",
        "options": [
          "کاملاً درست",
          "تقریباً درست",
          "تا حدی درست",
          "تقریباً نادرست",
          "کاملاً نادرست"
        ]
      },
      "user_answered": "1"
    },
    {
      "type": "text",
      "text": "اظهار منفی دیگران درباره همسرم، در روابط خانوادگی‌مان تأثیری ندارد.",
      "answer": {
        "type": "optional",
        "options": [
          "کاملاً درست",
          "تقریباً درست",
          "تا حدی درست",
          "تقریباً نادرست",
          "کاملاً نادرست"
        ]
      },
      "user_answered": "5"
    }
  ],
  "prerequisites": [
    {
      "type": "text",
      "label": "gender",
      "text": "جنسیت",
      "answer": { "type": "select", "options": ["زن", "مرد"] },
      "alias": "gender",
      "force": true,
      "user_answered": "1"
    },
    {
      "type": "text",
      "label": "age",
      "text": "سن",
      "answer": { "type": "number" },
      "alias": "age",
      "force": true,
      "user_answered": "30"
    },
    {
      "type": "text",
      "label": "education",
      "text": "تحصیلات",
      "answer": {
        "type": "select",
        "options": [
          "ابتدایی اول",
          "ابتدایی دوم",
          "متوسطه اول",
          "متوسطه دوم",
          "دیپلم",
          "کارشناسی",
          "کارشناسی ارشد",
          "پزشکی عمومی",
          "متخصص",
          "دکتری تخصصی",
          "حوزوی مقدمات",
          "حوزوی سطح۱",
          "حوزوی سطح۲",
          "حوزوی سطح۳",
          "حوزوی سطح۴"
        ]
      },
      "alias": "education",
      "force": true,
      "user_answered": "2"
    },
    {
      "type": "text",
      "label": "marital_status",
      "text": "وضعیت تأهل",
      "answer": { "type": "select", "options": ["مجرد", "متأهل"] },
      "alias": "marital_status",
      "force": true,
      "user_answered": "2"
    }
  ],
  "cornometer": 0,
  "score": { "penetrability_raw": 23, "penetrability_percentage": 0.41 },
  "score_current_version": "1.0.0",
  "score_last_version": "1.0.0"
}
